Workbook
Name aporte: FII!#REF!
Name patrimonio: FII!$E$17
Name percentual_investido: FII!$E$12
Name prazo: FII!$E$14
Name qtd_anos: FII!$E$14
Name rendimento_carteira: FII!$E$13
Name salario: FII!$E$11
Name sugestao_investimento: FII!#REF!
Name taxa_mensal: FII!$E$15

Sheet FII
C10: INFORMAÇÕES
C11: Salário | E11: 30000
C12: Percentual do Salário que será investido | E12: 0.1
C13: Rendimento Carteira | E13: 0.008
C14: Por quanrtos anos? | E14: 5
C15: Taxa de rendimento mensal? | E15: 0.01079
C16: Investimento Mensal | E16: =salario*E12 -> 3000
C17: Patrimônio Acumulado | E17: =FV(taxa_mensal,qtd_anos*12,$E$16*(-1)) -> 251330.74
C18: Dividendos mensais | E18: =E17*$E$13 -> 2010.6459
C20: CENÁRIOS
C21: Tempo | D21: Patrimônio Acumulado | E21: Dividendos
B22: 2 | C22: Quanto em 2 anos? | D22: =FV($E$15,B22*12,$E$16*-1) -> 81682.882 | E22: =D22*rendimento_carteira -> 653.46306
B23: 5 | C23: Quanto em 5 anos? | D23: =FV($E$15,B23*12,$E$16*-1) -> 251330.74 | E23: =D23*rendimento_carteira -> 2010.6459
B24: 10 | C24: Quanto em 10 anos? | D24: =FV($E$15,B24*12,$E$16*-1) -> 729852.64 | E24: =D24*rendimento_carteira -> 5838.8211
B25: 20 | C25: Quanto em 20 anos? | D25: =FV($E$15,B25*12,$E$16*-1) -> 3375595.2 | E25: =D25*rendimento_carteira -> 27004.762
B26: 30 | C26: Quanto em 30 anos? | D26: =FV($E$15,B26*12,$E$16*-1) -> 12966509 | E26: =D26*rendimento_carteira -> 103732.07
C28: SIMULADOR DE PERCENTUAIS INVESTIDOS
C29: QUAL O SEU PERFIL DE INVESTIDOR? | E29: CONSERVADOR
C30: VALOR A SER INVESTIDO POR MÊS | E30: =E16 -> 3000
C32: TIPO FII | D32: Percentual Sugerido | E32: Valores
C33: PAPEL | D33: =VLOOKUP($E$29&"-"&C33,'Tabela Complementar'!$A:$D,4,0) -> 0.3 | E33: =$E$30*D33 -> 900
C34: TIJOLO | D34: =VLOOKUP($E$29&"-"&C34,'Tabela Complementar'!$A:$D,4,0) -> 0.5 | E34: =$E$30*D34 -> 1500
C35: HIBRIDOS | D35: =VLOOKUP($E$29&"-"&C35,'Tabela Complementar'!$A:$D,4,0) -> 0.1 | E35: =$E$30*D35 -> 300
C36: FOFs | D36: =VLOOKUP($E$29&"-"&C36,'Tabela Complementar'!$A:$D,4,0) -> 0.1 | E36: =$E$30*D36 -> 300
C37: DESENVOLVIMENTO | D37: =VLOOKUP($E$29&"-"&C37,'Tabela Complementar'!$A:$D,4,0) -> 0 | E37: =$E$30*D37 -> 0
C38: HOTELARIAS | D38: =VLOOKUP($E$29&"-"&C38,'Tabela Complementar'!$A:$D,4,0) -> 0 | E38: =$E$30*D38 -> 0
E39: =SUM(E33:E38) -> 3000

Sheet Tabela Complementar
A13: CHAVE COMPOSTA | B13: PERFIL | C13: TIPO FII | D13: TIPO FII
A14: =B14&"-"&C14 -> CONSERVADOR-PAPEL | B14: CONSERVADOR | C14: PAPEL | D14: 0.3
A15: =B15&"-"&C15 -> CONSERVADOR-TIJOLO | B15: CONSERVADOR | C15: TIJOLO | D15: 0.5
A16: =B16&"-"&C16 -> CONSERVADOR-HIBRIDOS | B16: CONSERVADOR | C16: HIBRIDOS | D16: 0.1
A17: =B17&"-"&C17 -> CONSERVADOR-FOFs | B17: CONSERVADOR | C17: FOFs | D17: 0.1
A18: =B18&"-"&C18 -> CONSERVADOR-DESENVOLVIMENTO | B18: CONSERVADOR | C18: DESENVOLVIMENTO | D18: 0
A19: =B19&"-"&C19 -> CONSERVADOR-HOTELARIAS | B19: CONSERVADOR | C19: HOTELARIAS | D19: 0
A20: =B20&"-"&C20 -> MODERADO-PAPEL | B20: MODERADO | C20: PAPEL | D20: 0.32
A21: =B21&"-"&C21 -> MODERADO-TIJOLO | B21: MODERADO | C21: TIJOLO | D21: 0.35
A22: =B22&"-"&C22 -> MODERADO-HIBRIDOS | B22: MODERADO | C22: HIBRIDOS | D22: 0.08
A23: =B23&"-"&C23 -> MODERADO-FOFs | B23: MODERADO | C23: FOFs | D23: 0.05
A24: =B24&"-"&C24 -> MODERADO-DESENVOLVIMENTO | B24: MODERADO | C24: DESENVOLVIMENTO | D24: 0.1
A25: =B25&"-"&C25 -> MODERADO-HOTELARIAS | B25: MODERADO | C25: HOTELARIAS | D25: 0.1
... A31: =B31&"-"&C31 -> AGRESSIVO-HOTELARIAS | B31: AGRESSIVO | C31: HOTELARIAS | D31: 0.1
